{
  "kind": "spec_vs_diff_report",
  "version": "1.0",
  "generatedAt": "2026-02-18T23:23:42.570Z",
  "summary": "The diff implements comprehensive UI enhancements with smooth animations, modern design updates, and micro-interactions across all sections. All seven requirements (REQ-10 through REQ-16) are addressed with page transitions, interactive element animations, staggered list animations, modal animations, loading states, typography improvements, and animated empty states. However, explicit prefers-reduced-motion media query handling is not evident in the diff.",
  "missing_requirements": [
    {
      "id": "REQ-11",
      "requirement": "Animations must respect user's prefers-reduced-motion accessibility preference",
      "reason": "While REQ-11 AC states 'Animations respect user's prefers-reduced-motion setting', the diff does not show explicit @media (prefers-reduced-motion: reduce) CSS rules or JavaScript checks to disable/reduce animations for users with this preference.",
      "evidence": [
        "frontend/src/index.css"
      ]
    }
  ],
  "hallucinated_features": [],
  "confidence": 0.85,
  "changed_files": [
    "frontend-file-summaries.txt",
    "frontend/src/App.tsx",
    "frontend/src/components/auth/LoginButton.tsx",
    "frontend/src/components/auth/ProfileSetupDialog.tsx",
    "frontend/src/components/content/BookmarkForm.tsx",
    "frontend/src/components/content/SavedContentForm.tsx",
    "frontend/src/components/empty-states/EmptyState.tsx",
    "frontend/src/components/ideas/IdeaForm.tsx",
    "frontend/src/components/layout/AppLayout.tsx",
    "frontend/src/components/layout/BottomNav.tsx",
    "frontend/src/components/layout/Header.tsx",
    "frontend/src/components/loading/SkeletonLoader.tsx",
    "frontend/src/components/reminders/ReminderForm.tsx",
    "frontend/src/index.css",
    "frontend/src/pages/BookmarksPage.tsx",
    "frontend/src/pages/BusinessCardPage.tsx",
    "frontend/src/pages/IdeasPage.tsx",
    "frontend/src/pages/RemindersPage.tsx",
    "frontend/src/pages/SavedContentPage.tsx",
    "frontend/tailwind.config.js",
    "project_state.json"
  ]
}